apdl/__init__.py
apdl/apdl.py
apdl/cli.py
apdl/utils.py
apdl-0.0.0.0.0.3.dist-info/entry_points.txt
apdl-0.0.0.0.0.3.dist-info/LICENSE
apdl-0.0.0.0.0.3.dist-info/WHEEL
apdl-0.0.0.0.0.3.dist-info/METADATA
apdl-0.0.0.0.0.3.dist-info/RECORD
