Metadata-Version: 2.3
Name: apdl
Version: 0.0.0.0.0.3
Summary: apdl - A Python package for downloading YouTube videos in MP3 and MP4 formats.
Author-email: BilalsBxp <bilalsaputra641@gmail.com>
Classifier: License :: OSI Approved :: MIT License
Project-URL: Home, https://pypi.org/project/apdl
